greedypy/__init__.py
greedypy/fileio.py
greedypy/greedypy.py
greedypy/greedypy_registration_method.py
greedypy/interface.py
greedypy/metrics.py
greedypy/optimizer.py
greedypy/regularizers.py
greedypy/transformer.py
greedypy-0.0.6.dist-info/LICENSE.txt
greedypy-0.0.6.dist-info/METADATA
greedypy-0.0.6.dist-info/WHEEL
greedypy-0.0.6.dist-info/top_level.txt
greedypy-0.0.6.dist-info/RECORD
