Metadata-Version: 2.1
Name: greedypy
Version: 0.0.6
Summary: Fast deformable registration in python
Home-page: https://github.com/GFleishman/greedypy
Author: Greg M. Fleishman
Author-email: greg.nli10me@gmail.com
License: MIT
Platform: UNKNOWN
Requires-Dist: argparse
Requires-Dist: numpy
Requires-Dist: scipy
Requires-Dist: nibabel
Requires-Dist: pynrrd
Requires-Dist: pyfftw
Requires-Dist: zarr
Requires-Dist: numcodecs
